reservoir_info/__init__.py
reservoir_info/bean/__init__.py
reservoir_info/bean/common/__init__.py
reservoir_info/bean/common/box.py
reservoir_info/bean/common/copy_grid.py
reservoir_info/bean/common/unit_converter.py
reservoir_info/bean/comp_module/__init__.py
reservoir_info/bean/comp_module/comp_module.py
reservoir_info/bean/comp_other/__init__.py
reservoir_info/bean/comp_other/perforation.py
reservoir_info/bean/general/__init__.py
reservoir_info/bean/general/general.py
reservoir_info/bean/grid/__init__.py
reservoir_info/bean/grid/dxv.py
reservoir_info/bean/grid/dyv.py
reservoir_info/bean/grid/dzv.py
reservoir_info/bean/grid/fipnum.py
reservoir_info/bean/grid/grid.py
reservoir_info/bean/grid/mult.py
reservoir_info/bean/grid/multiporo.py
reservoir_info/bean/grid/nmatopts.py
reservoir_info/bean/grid/perm.py
reservoir_info/bean/grid/poro.py
reservoir_info/bean/grid/porv.py
reservoir_info/bean/grid/tops.py
reservoir_info/bean/props/__init__.py
reservoir_info/bean/props/density.py
reservoir_info/bean/props/props.py
reservoir_info/bean/props/pvdg.py
reservoir_info/bean/props/pvdo.py
reservoir_info/bean/props/pvto.py
reservoir_info/bean/props/pvtw.py
reservoir_info/bean/props/rel_permeate_model.py
reservoir_info/bean/props/rock.py
reservoir_info/bean/props/sgof.py
reservoir_info/bean/props/swof.py
reservoir_info/bean/result/__init__.py
reservoir_info/bean/result/well_product_record.py
reservoir_info/bean/result/well_production.py
reservoir_info/bean/result/well_productions.py
reservoir_info/bean/result/well_status.py
reservoir_info/bean/result/well_statuses.py
reservoir_info/bean/schedule/__init__.py
reservoir_info/bean/schedule/group_well.py
reservoir_info/bean/schedule/perforate_well.py
reservoir_info/bean/schedule/rpt_sched.py
reservoir_info/bean/schedule/schedule.py
reservoir_info/bean/schedule/recurrent/__init__.py
reservoir_info/bean/schedule/recurrent/recurrent.py
reservoir_info/bean/schedule/recurrent/stream_well.py
reservoir_info-0.1.72.dist-info/METADATA
reservoir_info-0.1.72.dist-info/WHEEL
reservoir_info-0.1.72.dist-info/top_level.txt
reservoir_info-0.1.72.dist-info/RECORD
