Metadata-Version: 2.4
Name: reservoir_info
Version: 0.1.72
Summary: 通用信息
Home-page: http://gitlab.magnetitech.com:8088/sources/reservoir/reservoir_info.git
Author: xlcao
Author-email: xl_cao@hotmail.com
Classifier: Programming Language :: Python :: 3
Classifier: License :: OSI Approved :: MIT License
Classifier: Operating System :: OS Independent
Requires-Python: >=3.6
Dynamic: author
Dynamic: author-email
Dynamic: classifier
Dynamic: description
Dynamic: description-content-type
Dynamic: home-page
Dynamic: requires-python
Dynamic: summary
